{
  "common": {
    "name": "icloud_devices",
    "version": "1.0.2",
    "news": {
      "1.0.2": {
        "en": "bugfix resetting tfa code",
        "de": "fehlerbehebung tfa-code",
        "ru": "bugfix сброс tfa код",
        "pt": "bugfix redefinindo o código tfa",
        "nl": "quality over quantity (qoq) reseting tfa code",
        "fr": "bugfix resetting code tfa",
        "it": "bugfix reset tfa codice",
        "es": "bugfix reseteo código tfa",
        "pl": "bugfix reseting tfa code",
        "uk": "javascript licenses api веб-сайт go1.13.8",
        "zh-cn": "b 混合法守则"
      },
      "1.0.1": {
        "en": "create config file if not exists",
        "de": "config datei erstellen, wenn nicht vorhanden",
        "ru": "создать config файл, если не существует",
        "pt": "criar arquivo de configuração se não existir",
        "nl": "creëer config bestand als hij niet bestaat",
        "fr": "créer un fichier de configuration s'il n'existe pas",
        "it": "creare file di configurazione se non esiste",
        "es": "crear archivo de configuración si no existe",
        "pl": "plik konfiguracyjny jeśli nie istnieje",
        "uk": "створити файл конфігурації, якщо не існує",
        "zh-cn": "如果没有存在,便可建立密封档案"
      },
      "1.0.0": {
        "en": "read tfa code from tfa-state, overwrite tfa method from lib to provide code not from std imput",
        "de": "tfa-code von tfa-state, überschreiben tfa-methode von lib, um code nicht von std imput",
        "ru": "читать tfa код из tfa-state, переписать метод tfa от lib, чтобы предоставить код не от std imput",
        "pt": "ler o código tfa de tfa-state, sobrescrever o método tfa da lib para fornecer código não da gota de std",
        "nl": "las tafacode van tfa-state, overschrijvingsmethode van lib om geen code te verstrekken van sten imput",
        "fr": "lire code tfa de tfa-state, overwrite tfa méthode de lib pour fournir le code non de std imput",
        "it": "leggere il codice tfa da tfa-state, sovrascrivere il metodo tfa da lib per fornire il codice non da std imput",
        "es": "read tfa code from tfa-state, overwrite tfa method from lib to provide code not from std imput",
        "pl": "czytanie kodu z tfa-state, nadpisuje metodę tfa z libu, aby zapewnić kod nie od std imput",
        "uk": "читати tfa код з tfa-state, перезапис tfa метод від lib, щоб забезпечити код не від std",
        "zh-cn": "简写法系:国家法、宽松的制法,以利布语提供不成图的编码。"
      },
      "0.2.0": {
        "en": "changed apple icloud api\nGit Ignore\nREADME",
        "de": "äpfel und äpfel\nGit Ignorieren\nBEGRÜNDUNG",
        "ru": "изменил яблоко icloud api\nGit Игнорировать\nЧИТАТЬ",
        "pt": "muda de maçã\nGit Ignorar\nREALIZAÇÃO",
        "nl": "api\nGit Ignore\nVERTALING:",
        "fr": "changé de pomme icloud api\nGit Ignore\nREADME",
        "it": "cambiato mela icloud api\nGit Ignore\nREADEM",
        "es": "cambio de manzana icloud api\nGit Ignore\nREADME",
        "pl": "zmienił jabłko api\nGit Ignore\nREADME",
        "uk": "змінений яблучний icloud api\nGit Ігнор\nЗАМОВИТИ",
        "zh-cn": "a. 装修\nGit Ignore\n建 议"
      },
      "0.1.0": {
        "en": "initial release",
        "de": "erstausstrahlung",
        "ru": "начальный выпуск",
        "pt": "lançamento inicial",
        "nl": "niet",
        "fr": "initial release",
        "it": "rilascio iniziale",
        "es": "liberación inicial",
        "pl": "pierwsze wydanie",
        "uk": "початковий реліз",
        "zh-cn": "初步释放"
      },
      "0.0.1": {
        "en": "initial release",
        "de": "Erstveröffentlichung",
        "ru": "Начальная версия",
        "pt": "lançamento inicial",
        "nl": "Eerste uitgave",
        "fr": "Première version",
        "it": "Versione iniziale",
        "es": "Versión inicial",
        "pl": "Pierwsze wydanie",
        "zh-cn": "首次出版",
        "uk": "початковий випуск"
      }
    },
    "title": "ICloud Devices",
    "titleLang": {
      "en": "ICloud Devices",
      "de": "ICloud-Geräte",
      "ru": "iCloud-устройства",
      "pt": "Dispositivos iCloud",
      "nl": "iCloud-apparaten",
      "fr": "Appareils ICloud",
      "it": "Dispositivi ICloud",
      "es": "Dispositivos iCloud",
      "pl": "Urządzenia ICloud",
      "zh-cn": "iCloud 设备",
      "uk": "Пристрої ICloud"
    },
    "desc": {
      "en": "Getting information like battery and location for ICloud devices",
      "de": "Abrufen von Informationen wie Akku und Standort für ICloud-Geräte",
      "ru": "Получение информации, такой как батарея и местоположение для устройств ICloud",
      "pt": "Obtendo informações como bateria e localização para dispositivos iCloud",
      "nl": "Informatie verkrijgen zoals batterij en locatie voor iCloud-apparaten",
      "fr": "Obtenir des informations telles que la batterie et l'emplacement des appareils ICloud",
      "it": "Ottenere informazioni come la batteria e la posizione per i dispositivi ICloud",
      "es": "Obtener información como la batería y la ubicación de los dispositivos ICloud",
      "pl": "Uzyskiwanie informacji, takich jak bateria i lokalizacja dla urządzeń ICloud",
      "zh-cn": "获取 ICloud 设备的电池和位置等信息",
      "uk": "Отримання таких відомостей, як акумулятор  місцезнаходження пристроїв ICloud"
    },
    "authors": [
      "spabas <bastian.spaeth@gmx.de>"
    ],
    "keywords": [
      "ioBroker",
      "template",
      "Smart Home",
      "home automation"
    ],
    "license": "MIT",
    "platform": "Javascript/Node.js",
    "main": "main.js",
    "icon": "icloud_devices.png",
    "enabled": true,
    "extIcon": "https://raw.githubusercontent.com/spabas/ioBroker.icloud_devices/main/admin/icloud_devices.png",
    "readme": "https://github.com/spabas/ioBroker.icloud_devices/blob/main/README.md",
    "loglevel": "info",
    "mode": "daemon",
    "type": "infrastructure",
    "compact": true,
    "connectionType": "cloud",
    "dataSource": "poll",
    "adminUI": {
      "config": "json"
    },
    "dependencies": [
      {
        "js-controller": ">=3.3.22"
      }
    ],
    "globalDependencies": [
      {
        "admin": ">=5.1.13"
      }
    ]
  },
  "native": {
    "username": "",
    "password": "",
    "update_interval": 120000
  },
  "objects": [],
  "instanceObjects": []
}
